{"configuration_dependency-management.md":"Bel08Kt3","examples_data-binding.md":"B2u2x74b","examples_jax-ws-binding.md":"CCHQGoEp","examples_overview.md":"DdqWZbKX","examples_remote-wsdl.md":"Cg4UytJ8","examples_service.md":"CObSLbRZ","examples_xjc-extensions.md":"XqYYLDWm","getting-started.md":"Ck-s0zP6","index.md":"BvvEfF9f","java-generation_overview.md":"Dh1sRW03","java-generation_task-api.md":"C0mxd8rU","java-generation_worker-api.md":"sdNop1c_","javascript-generation_overview.md":"Cxe-nXC_","javascript-generation_task-api.md":"DC0fMhdl","javascript-generation_worker-api.md":"BuQu9GXg","overview.md":"B0hJx9F6"}